tonic_fabricate/__init__.py
tonic_fabricate/client.py
tonic_fabricate-1.0.2.dist-info/METADATA
tonic_fabricate-1.0.2.dist-info/WHEEL
tonic_fabricate-1.0.2.dist-info/top_level.txt
tonic_fabricate-1.0.2.dist-info/RECORD
