Metadata-Version: 2.4
Name: tonic-fabricate
Version: 1.0.2
Summary: The official Fabricate client for Python
Home-page: https://github.com/fabricate-tools/client-python
Author: Fabricate Tools
License-Expression: MIT
Project-URL: Homepage, https://github.com/fabricate-tools/client-python
Project-URL: Repository, https://github.com/fabricate-tools/client-python
Project-URL: Documentation, https://github.com/fabricate-tools/client-python#readme
Classifier: Development Status :: 4 - Beta
Classifier: Intended Audience :: Developers
Classifier: Operating System :: OS Independent
Classifier: Programming Language :: Python :: 3
Classifier: Programming Language :: Python :: 3.8
Classifier: Programming Language :: Python :: 3.9
Classifier: Programming Language :: Python :: 3.10
Classifier: Programming Language :: Python :: 3.11
Classifier: Programming Language :: Python :: 3.12
Requires-Python: >=3.8
Requires-Dist: requests>=2.25.0
Requires-Dist: tomli>=1.2.0; python_version < "3.11"
Provides-Extra: dev
Requires-Dist: python-dotenv>=0.19.0; extra == "dev"
Requires-Dist: pytest>=6.0.0; extra == "dev"
Requires-Dist: black>=22.0.0; extra == "dev"
Requires-Dist: flake8>=4.0.0; extra == "dev"
Requires-Dist: mypy>=0.900; extra == "dev"
Dynamic: home-page
Dynamic: requires-python
